variant_extractor/VariantExtractor.py
variant_extractor/__init__.py
variant_extractor/variants.py
variant_extractor/private/_PendingBreakends.py
variant_extractor/private/__init__.py
variant_extractor/private/_parser.py
variant_extractor/private/_utils.py
variant_extractor-5.0.0.dist-info/LICENSE
variant_extractor-5.0.0.dist-info/METADATA
variant_extractor-5.0.0.dist-info/WHEEL
variant_extractor-5.0.0.dist-info/top_level.txt
variant_extractor-5.0.0.dist-info/RECORD
