Metadata-Version: 2.1
Name: variant-extractor
Version: 5.0.0
Summary: Deterministic and standard extractor of indels, SNVs and structural variants (SVs) from VCF files.
Author-email: Rapsssito <contact@rodrigomartin.dev>
License: MIT
Project-URL: homepage, https://github.com/EUCANCan/variant-extractor
Project-URL: issues, https://github.com/EUCANCan/variant-extractor/issues
Project-URL: repository, https://github.com/EUCANCan/variant-extractor.git
Project-URL: documentation, https://EUCANCan.github.io/variant-extractor/
Keywords: vcf,genetics,bioinformatics,variant,indel,snv,sv
Classifier: Programming Language :: Python :: 3 :: Only
Classifier: Development Status :: 5 - Production/Stable
Classifier: Operating System :: OS Independent
Requires-Python: >=3.6
License-File: LICENSE
Requires-Dist: pysam>=0.22.1
Provides-Extra: build
Requires-Dist: build~=1.2; extra == "build"
Provides-Extra: docs
Requires-Dist: sphinx; extra == "docs"
Requires-Dist: sphinx-rtd-theme; extra == "docs"
Requires-Dist: myst-parser; extra == "docs"
Requires-Dist: docutils>=0.18.0; extra == "docs"
